pyrebase/__init__.py
pyrebase/pyre_sseclient.py
pyrebase/pyrebase.py
pyrebase4-4.9.0.dist-info/METADATA
pyrebase4-4.9.0.dist-info/WHEEL
pyrebase4-4.9.0.dist-info/top_level.txt
pyrebase4-4.9.0.dist-info/RECORD
