Metadata-Version: 2.1
Name: Pyrebase4
Version: 4.9.0
Summary: A simple python wrapper for the Firebase API with current deps
Home-page: https://github.com/nhorvath/Pyrebase4
Author: nhorvath
License: MIT
Keywords: Firebase
Classifier: Development Status :: 3 - Alpha
Classifier: Intended Audience :: Developers
Classifier: License :: OSI Approved :: MIT License
Classifier: Programming Language :: Python :: 3.4
Requires-Dist: requests-toolbelt>=1.0.0
Requires-Dist: requests>=2.31
Requires-Dist: urllib3<2,>=1.21.1
Requires-Dist: google-cloud-storage>=2.18.2
Requires-Dist: oauth2client>=4.1.2
Requires-Dist: python-jwt>=2.0.1
Requires-Dist: pycryptodome>=3.6.4
